<?xml version="1.0" encoding="UTF-8"?>
<MF0 version="1.1" packageUris="http://schema.mathworks.com/mf0/sl_modelref_info/R2018b">
  <ModelRefInfoRepo.ModelRefInfoRoot type="ModelRefInfoRepo.ModelRefInfoRoot" uuid="04c6ed9f-3ff5-45f4-aa6f-6fd0eab617b5">
    <autoSolverStatusFlags>327</autoSolverStatusFlags>
    <childModelRefInfo type="ModelRefInfoRepo.ChildModelRefInfo" uuid="0694b512-c741-4e0b-821b-469ea8cb5602">
      <modelName>fMPC</modelName>
      <modelPath>fMPC</modelPath>
    </childModelRefInfo>
    <dataDictionary>f_mpc.sldd</dataDictionary>
    <dataDictionarySet>f_mpc.sldd</dataDictionarySet>
    <dataDictionarySetForDataTypeCheck>f_mpc.sldd</dataDictionarySetForDataTypeCheck>
    <dataTransferInfos>AAFJTQAAAAAOAAAAOAAAAAYAAAAIAAAAAgAAAAAAAAAFAAAACAAAAAAAAAABAAAAAQAAAAAAAAAFAAQAAQAAAAEAAAAAAAAA</dataTransferInfos>
    <fundamentalSampleTimePeriod>0.20000000000000001</fundamentalSampleTimePeriod>
    <globalVariables>A</globalVariables>
    <globalVariables>At</globalVariables>
    <globalVariables>B</globalVariables>
    <globalVariables>Bt</globalVariables>
    <globalVariables>Q</globalVariables>
    <globalVariables>Qf</globalVariables>
    <globalVariables>R</globalVariables>
    <globalVariables>T</globalVariables>
    <globalVariables>eyem</globalVariables>
    <globalVariables>eyen</globalVariables>
    <globalVariables>kappa</globalVariables>
    <globalVariables>m</globalVariables>
    <globalVariables>n</globalVariables>
    <globalVariables>niters</globalVariables>
    <globalVariables>nm</globalVariables>
    <globalVariables>nz</globalVariables>
    <globalVariables>x0</globalVariables>
    <globalVariables>z0</globalVariables>
    <globalVariables>zmax</globalVariables>
    <globalVariables>zmin</globalVariables>
    <loggingSaveFormat>2</loggingSaveFormat>
    <maxFreqHz>-1</maxFreqHz>
    <runtimeNonFcnCallRateInfos type="ModelRefInfoRepo.RateInfo">
      <compiled>true</compiled>
      <nonFcnCallPartitionName>D1</nonFcnCallPartitionName>
      <period>0.20000000000000001</period>
      <rateIdx>0</rateIdx>
    </runtimeNonFcnCallRateInfos>
    <sampleTimeInheritanceRule>2</sampleTimeInheritanceRule>
    <timingAndTaskingRegistry>&lt;?xml version=&quot;1.0&quot;?&gt;
&lt;MF0 version=&quot;1.1&quot; packageUris=&quot;http://schema.mathworks.com/mf0/slexec_mm_sto/R2018b&quot;&gt;
  &lt;sto.Registry type=&quot;sto.Registry&quot; uuid=&quot;039fb4db-7cce-45f4-bb4d-9db54c8028d0&quot;&gt;
    &lt;clocks type=&quot;sto.Clock&quot; uuid=&quot;fb044821-2b88-4029-851f-1490e1f5a372&quot;&gt;
      &lt;clockTickConstraint&gt;PeriodicWithFixedResolution&lt;/clockTickConstraint&gt;
      &lt;needsToProvideTimeDuringExecution&gt;true&lt;/needsToProvideTimeDuringExecution&gt;
      &lt;resolution&gt;0.20000000000000001&lt;/resolution&gt;
      &lt;specifiedClockTickConstraint&gt;PeriodicWithFixedResolution&lt;/specifiedClockTickConstraint&gt;
      &lt;clockDomain type=&quot;sto.ClockDomain&quot; uuid=&quot;803a7ff3-1499-48d0-96d6-832ea4c10bb7&quot;&gt;
        &lt;baseTaskID&gt;_task0&lt;/baseTaskID&gt;
        &lt;computedFundamentalStepSize&gt;0.20000000000000001&lt;/computedFundamentalStepSize&gt;
        &lt;rates type=&quot;sto.Rate&quot; uuid=&quot;468972b9-eea0-4e36-84d7-7d1318b8b21f&quot;/&gt;
        &lt;rates type=&quot;sto.Rate&quot; uuid=&quot;45ce603e-707b-413a-b32f-57b902a354d1&quot;/&gt;
        &lt;rootTaskHierarchyElements type=&quot;sto.Task&quot; uuid=&quot;136cab15-4f5a-4e9f-8dd3-4547cbcb0521&quot;&gt;
          &lt;isExecutable&gt;true&lt;/isExecutable&gt;
          &lt;orderIndex&gt;1&lt;/orderIndex&gt;
          &lt;rates type=&quot;sto.Rate&quot; uuid=&quot;468972b9-eea0-4e36-84d7-7d1318b8b21f&quot;&gt;
            &lt;annotation&gt;FiM&lt;/annotation&gt;
            &lt;colorIndex&gt;8&lt;/colorIndex&gt;
            &lt;description&gt;Fixed in Minor Step&lt;/description&gt;
            &lt;eventSourceType&gt;UNSPECIFIED_EVENT_SOURCE&lt;/eventSourceType&gt;
            &lt;rateIDX&gt;-1&lt;/rateIDX&gt;
            &lt;registry type=&quot;sto.Registry&quot; uuid=&quot;039fb4db-7cce-45f4-bb4d-9db54c8028d0&quot;/&gt;
            &lt;taskId&gt;_task0&lt;/taskId&gt;
            &lt;useForExecution&gt;NotForExecution&lt;/useForExecution&gt;
            &lt;rateSpec type=&quot;sto.RateSpec&quot; uuid=&quot;71d98a96-ca9c-443f-b3c6-7bf8d8f63efd&quot;&gt;
              &lt;offset&gt;1&lt;/offset&gt;
              &lt;rateType&gt;ZOHContinuous&lt;/rateType&gt;
            &lt;/rateSpec&gt;
          &lt;/rates&gt;
          &lt;rates type=&quot;sto.Rate&quot; uuid=&quot;45ce603e-707b-413a-b32f-57b902a354d1&quot;&gt;
            &lt;annotation&gt;D1&lt;/annotation&gt;
            &lt;colorIndex&gt;2&lt;/colorIndex&gt;
            &lt;description&gt;Discrete 1&lt;/description&gt;
            &lt;eventSourceType&gt;UNSPECIFIED_EVENT_SOURCE&lt;/eventSourceType&gt;
            &lt;registry type=&quot;sto.Registry&quot; uuid=&quot;039fb4db-7cce-45f4-bb4d-9db54c8028d0&quot;/&gt;
            &lt;taskId&gt;_task0&lt;/taskId&gt;
            &lt;rateSpec type=&quot;sto.RateSpec&quot; uuid=&quot;7e4b0591-d35b-4e26-b8f9-7655cac67d3f&quot;&gt;
              &lt;period&gt;0.20000000000000001&lt;/period&gt;
              &lt;rateType&gt;ClassicPeriodicDiscrete&lt;/rateType&gt;
            &lt;/rateSpec&gt;
          &lt;/rates&gt;
          &lt;elementType&gt;Task&lt;/elementType&gt;
          &lt;identifier&gt;_task0&lt;/identifier&gt;
          &lt;priority&gt;40&lt;/priority&gt;
        &lt;/rootTaskHierarchyElements&gt;
      &lt;/clockDomain&gt;
    &lt;/clocks&gt;
    &lt;executionSpec&gt;Undetermined&lt;/executionSpec&gt;
    &lt;taskDependencyGraph type=&quot;sto.SerializedTaskConnectionList&quot; uuid=&quot;0c77bc1e-0bd1-4746-8b84-54737e5024f1&quot;&gt;
      &lt;taskIdentifier&gt;_task0&lt;/taskIdentifier&gt;
    &lt;/taskDependencyGraph&gt;
    &lt;taskPriorityDirection&gt;HighNumberLast&lt;/taskPriorityDirection&gt;
    &lt;tasks type=&quot;sto.Task&quot; uuid=&quot;136cab15-4f5a-4e9f-8dd3-4547cbcb0521&quot;/&gt;
  &lt;/sto.Registry&gt;
&lt;/MF0&gt;</timingAndTaskingRegistry>
    <FMUBlockMap type="ModelRefInfoRepo.FMUBlockInfo" uuid="91e77679-157c-4b0b-95c3-79fa4f01454e"/>
    <codeGenInfo type="ModelRefInfoRepo.CodeGenInformation" uuid="4232d073-86db-4429-9be6-3047f0bc9807"/>
    <configSettingsForConsistencyChecks type="ModelRefInfoRepo.ConfigSettingsForConsistencyChecks" uuid="e67ec981-879d-4377-8b1f-a693d2db1cd3">
      <consistentOutportInitialization>true</consistentOutportInitialization>
      <fixedStepSize>0.20000000000000001</fixedStepSize>
      <frameDiagnosticSetting>2</frameDiagnosticSetting>
      <hasHybridSampleTime>true</hasHybridSampleTime>
      <signalLoggingSaveFormat>2</signalLoggingSaveFormat>
      <solverName>FixedStepDiscrete</solverName>
      <solverType>SOLVER_TYPE_FIXEDSTEP</solverType>
      <hardwareSettings type="ModelRefInfoRepo.HardwareSettings" uuid="79c4debe-5692-4c11-b63e-1ec5cdee30f0">
        <prodBitPerChar>8</prodBitPerChar>
        <prodBitPerDouble>64</prodBitPerDouble>
        <prodBitPerFloat>32</prodBitPerFloat>
        <prodBitPerInt>32</prodBitPerInt>
        <prodBitPerLong>32</prodBitPerLong>
        <prodBitPerLongLong>64</prodBitPerLongLong>
        <prodBitPerPointer>64</prodBitPerPointer>
        <prodBitPerPtrDiffT>64</prodBitPerPtrDiffT>
        <prodBitPerShort>16</prodBitPerShort>
        <prodBitPerSizeT>64</prodBitPerSizeT>
        <prodEndianess>1</prodEndianess>
        <prodShiftRight>true</prodShiftRight>
        <prodWordSize>64</prodWordSize>
      </hardwareSettings>
    </configSettingsForConsistencyChecks>
    <dataPortGroup type="ModelRefInfoRepo.DataPortGroup" uuid="689ac2c9-eec5-4596-85e8-28424618f302"/>
    <interfaceParameterInfo type="ModelRefInfoRepo.InterfaceParameterInfo" uuid="dfd42a9e-04a3-4489-ade7-b8987459e9b2">
      <globalVariables type="ModelRefInfoRepo.BuiltinParameter" uuid="70ff7c6a-d157-4781-852c-7cceab5db03a">
        <dimensions>12</dimensions>
        <dimensions>12</dimensions>
        <isUsed>true</isUsed>
        <numDimensions>2</numDimensions>
        <parameterName>A</parameterName>
      </globalVariables>
      <globalVariables type="ModelRefInfoRepo.BuiltinParameter" uuid="e5cadd97-3dcb-4f2e-b181-effc248fffab">
        <dimensions>12</dimensions>
        <dimensions>12</dimensions>
        <isUsed>true</isUsed>
        <numDimensions>2</numDimensions>
        <parameterName>At</parameterName>
      </globalVariables>
      <globalVariables type="ModelRefInfoRepo.BuiltinParameter" uuid="3caa8cea-fc05-44cf-a5fc-704f6816a289">
        <dimensions>12</dimensions>
        <dimensions>3</dimensions>
        <isUsed>true</isUsed>
        <numDimensions>2</numDimensions>
        <parameterName>B</parameterName>
      </globalVariables>
      <globalVariables type="ModelRefInfoRepo.BuiltinParameter" uuid="5cd326d6-96eb-404c-afb1-ededfe295934">
        <dimensions>3</dimensions>
        <dimensions>12</dimensions>
        <isUsed>true</isUsed>
        <numDimensions>2</numDimensions>
        <parameterName>Bt</parameterName>
      </globalVariables>
      <globalVariables type="ModelRefInfoRepo.BuiltinParameter" uuid="8aa763d9-8d1a-4dbe-87be-46a5a1bb9fda">
        <dimensions>12</dimensions>
        <dimensions>12</dimensions>
        <isUsed>true</isUsed>
        <numDimensions>2</numDimensions>
        <parameterName>Q</parameterName>
      </globalVariables>
      <globalVariables type="ModelRefInfoRepo.BuiltinParameter" uuid="04c22726-1202-4635-9c89-c24f7e9388e9">
        <dimensions>12</dimensions>
        <dimensions>12</dimensions>
        <isUsed>true</isUsed>
        <numDimensions>2</numDimensions>
        <parameterName>Qf</parameterName>
      </globalVariables>
      <globalVariables type="ModelRefInfoRepo.BuiltinParameter" uuid="a271d06e-4f28-4fae-94f5-b8b37be9edf3">
        <dimensions>3</dimensions>
        <dimensions>3</dimensions>
        <isUsed>true</isUsed>
        <numDimensions>2</numDimensions>
        <parameterName>R</parameterName>
      </globalVariables>
      <globalVariables type="ModelRefInfoRepo.BuiltinParameter" uuid="3d08f4c8-835e-47f3-ba1a-64ec5b9344dd">
        <dimensions>3</dimensions>
        <dimensions>3</dimensions>
        <isUsed>true</isUsed>
        <numDimensions>2</numDimensions>
        <parameterName>eyem</parameterName>
      </globalVariables>
      <globalVariables type="ModelRefInfoRepo.BuiltinParameter" uuid="d0fdaf2f-8e92-49b4-9b97-003faaedc777">
        <dimensions>12</dimensions>
        <dimensions>12</dimensions>
        <isUsed>true</isUsed>
        <numDimensions>2</numDimensions>
        <parameterName>eyen</parameterName>
      </globalVariables>
      <globalVariables type="ModelRefInfoRepo.BuiltinParameter" uuid="423c5e5f-94f1-477e-93b6-b0c53e813192">
        <dimensions>1</dimensions>
        <dimensions>1</dimensions>
        <isUsed>true</isUsed>
        <numDimensions>2</numDimensions>
        <parameterName>kappa</parameterName>
      </globalVariables>
      <globalVariables type="ModelRefInfoRepo.BuiltinParameter" uuid="e83d3bd1-b52f-46e6-8d9f-ce06a3583fe0">
        <dimensions>1</dimensions>
        <dimensions>1</dimensions>
        <isUsed>true</isUsed>
        <numDimensions>2</numDimensions>
        <parameterName>nm</parameterName>
      </globalVariables>
      <globalVariables type="ModelRefInfoRepo.BuiltinParameter" uuid="c9934b1d-ddc6-44e8-bb55-ea7d935b10b3">
        <dimensions>12</dimensions>
        <dimensions>1</dimensions>
        <isUsed>true</isUsed>
        <numDimensions>2</numDimensions>
        <parameterName>x0</parameterName>
      </globalVariables>
      <globalVariables type="ModelRefInfoRepo.BuiltinParameter" uuid="7255dc58-5a86-4767-b21f-e048ff12c669">
        <dimensions>15</dimensions>
        <dimensions>10</dimensions>
        <isUsed>true</isUsed>
        <numDimensions>2</numDimensions>
        <parameterName>z0</parameterName>
      </globalVariables>
      <globalVariables type="ModelRefInfoRepo.BuiltinParameter" uuid="fa5f0cf1-cceb-4edc-96ee-365f864b5aa0">
        <dimensions>15</dimensions>
        <dimensions>10</dimensions>
        <isUsed>true</isUsed>
        <numDimensions>2</numDimensions>
        <parameterName>zmax</parameterName>
      </globalVariables>
      <globalVariables type="ModelRefInfoRepo.BuiltinParameter" uuid="8d893964-f525-4fee-8d42-7c3f2f7b3b16">
        <dimensions>15</dimensions>
        <dimensions>10</dimensions>
        <isUsed>true</isUsed>
        <numDimensions>2</numDimensions>
        <parameterName>zmin</parameterName>
      </globalVariables>
      <globalVariables type="ModelRefInfoRepo.BuiltinParameter" uuid="2c3ffd62-06f2-4410-bbab-cafd68b20bf4">
        <datatypeID>6</datatypeID>
        <dimensions>1</dimensions>
        <dimensions>1</dimensions>
        <isUsed>true</isUsed>
        <numDimensions>2</numDimensions>
        <parameterName>T</parameterName>
      </globalVariables>
      <globalVariables type="ModelRefInfoRepo.BuiltinParameter" uuid="d2a98904-6977-4e24-9a87-611029b48187">
        <datatypeID>6</datatypeID>
        <dimensions>1</dimensions>
        <dimensions>1</dimensions>
        <isUsed>true</isUsed>
        <numDimensions>2</numDimensions>
        <parameterName>m</parameterName>
      </globalVariables>
      <globalVariables type="ModelRefInfoRepo.BuiltinParameter" uuid="4454a309-98e6-4033-a208-5df6f437b68e">
        <datatypeID>6</datatypeID>
        <dimensions>1</dimensions>
        <dimensions>1</dimensions>
        <isUsed>true</isUsed>
        <numDimensions>2</numDimensions>
        <parameterName>n</parameterName>
      </globalVariables>
      <globalVariables type="ModelRefInfoRepo.BuiltinParameter" uuid="299a818f-e6a1-40c1-83e7-eefd3d38f18f">
        <datatypeID>6</datatypeID>
        <dimensions>1</dimensions>
        <dimensions>1</dimensions>
        <isUsed>true</isUsed>
        <numDimensions>2</numDimensions>
        <parameterName>niters</parameterName>
      </globalVariables>
      <globalVariables type="ModelRefInfoRepo.BuiltinParameter" uuid="141085d1-8987-4ace-b986-57574645c4bd">
        <datatypeID>6</datatypeID>
        <dimensions>1</dimensions>
        <dimensions>1</dimensions>
        <isUsed>true</isUsed>
        <numDimensions>2</numDimensions>
        <parameterName>nz</parameterName>
      </globalVariables>
    </interfaceParameterInfo>
    <methodInfo type="ModelRefInfoRepo.MethodExistenceInfo" uuid="2e461e48-0480-424a-b0b0-dd8d2784c6b4">
      <hasEnableMethod>true</hasEnableMethod>
      <hasSystemInitializeMethod>true</hasSystemInitializeMethod>
      <hasSystemResetMethod>true</hasSystemResetMethod>
      <hasTerminateMethod>true</hasTerminateMethod>
      <hasUpdateMethod>true</hasUpdateMethod>
    </methodInfo>
    <periodicEventPortUnsupportedBlockInfo type="ModelRefInfoRepo.PeriodicEventPortUnsupportedBlockInfo" uuid="d01d3435-2a95-42ae-a777-ce99010880ec"/>
    <portGroupsRequireSameRate type="ModelRefInfoRepo.PortGroupsRequireSameRate" uuid="1fb06d34-6be0-4948-b6bb-6b0b632326cd">
      <DSMPortGroups type="ModelRefInfoRepo.NameToPortGroupIdxVectMap" uuid="1a2a8c8c-e61a-4453-a1a8-83be4d71d2e1"/>
      <GlobalDSMPortGroups type="ModelRefInfoRepo.NameToPortGroupIdxVectMap" uuid="897f9f1f-bebe-4808-a067-739b8f842f22"/>
      <mergedPortGroups type="ModelRefInfoRepo.NameToPortGroupIdxVectMap" uuid="79c6aa4b-57c9-4de4-b426-447faaae4b56"/>
    </portGroupsRequireSameRate>
    <rateSpecOfGlobalDSMAccessedByDescExpFcnMdlMap type="ModelRefInfoRepo.GlobalDSMRateSpecMap" uuid="8026c9e3-167c-4492-bd7f-4ee11dfbabdf"/>
    <simulinkFunctions type="ModelRefInfoRepo.SimulinkFunctions" uuid="4031270b-1e3c-4933-ae40-320dd87c7623">
      <compServicePortMap>AAFJTQAAAAAOAAAAMAAAAAYAAAAIAAAABgAAAAAAAAAFAAAACAAAAAAAAAAAAAAAAQAAAAAAAAAJAAAAAAAAAA==</compServicePortMap>
      <compSimulinkFunctionCatalog></compSimulinkFunctionCatalog>
      <variantSimulinkFunctions type="ModelRefInfoRepo.VariantSimulinkFunctions" uuid="9f6d45d7-2894-4618-81b1-cf9f35c78325"/>
    </simulinkFunctions>
    <stateWriterToOwnerMap type="ModelRefInfoRepo.StateWriterInfo" uuid="7bc746ba-0a66-42e3-b5ec-8d8f1dccb4cf"/>
  </ModelRefInfoRepo.ModelRefInfoRoot>
</MF0>